distworker/__init__.py
distworker/py.typed
distworker/setup.py
distworker/client/__init__.py
distworker/client/auth.py
distworker/client/exceptions.py
distworker/client/request.py
distworker/client/task.py
distworker/client/worker.py
distworker/protocol/__init__.py
distworker/protocol/protocol_pb2.py
distworker/protocol/protocol_pb2.pyi
distworker_sdk-0.0.6.dist-info/licenses/LICENSE
distworker_sdk-0.0.6.dist-info/METADATA
distworker_sdk-0.0.6.dist-info/WHEEL
distworker_sdk-0.0.6.dist-info/top_level.txt
distworker_sdk-0.0.6.dist-info/RECORD
