Metadata-Version: 2.4
Name: distworker-sdk
Version: 0.0.6
Summary: Python SDK for DistWorker distributed task processing system
Home-page: https://github.com/jc-lab/distworker
Author: JC-Lab
Author-email: JC-Lab <joseph@jc-lab.net>
License-Expression: Apache-2.0
Project-URL: Homepage, https://github.com/jc-lab/distworker
Project-URL: Bug Reports, https://github.com/jc-lab/distworker/issues
Project-URL: Source, https://github.com/jc-lab/distworker
Project-URL: Documentation, https://github.com/jc-lab/distworker/blob/main/README.md
Keywords: distributed,worker,task
Classifier: Development Status :: 4 - Beta
Classifier: Intended Audience :: Developers
Classifier: Operating System :: OS Independent
Classifier: Programming Language :: Python :: 3
Classifier: Programming Language :: Python :: 3.11
Classifier: Programming Language :: Python :: 3.12
Classifier: Topic :: Software Development :: Libraries :: Python Modules
Classifier: Topic :: System :: Distributed Computing
Requires-Python: >=3.11
License-File: LICENSE
Requires-Dist: websockets>=11.0.0
Requires-Dist: protobuf>=6.31.1
Requires-Dist: googleapis-common-protos>=1.59.0
Requires-Dist: psutil>=5.9.0
Dynamic: author
Dynamic: home-page
Dynamic: license-file
Dynamic: requires-python
